{
    "D003_0": [
        {
            "params1": "FF 03 02 47",
            "params2": "FF 5F FF FF",
            "posx": -317.74249267578125,
            "posy": 0.0,
            "posz": 2630.0,
            "anglex": 65535,
            "angley": 16384,
            "anglez": 65535,
            "id": "FC 28",
            "name": "saveObj",
            "extra_info": {
                "scenefid": 71,
                "scenef": "scene flag: 0x9 80",
                "subtype": "dungeon",
                "scen_link": 3,
                "saveobj_name_id": 255,
                "name": "Bird Statue"
            },
            "type": "OBJS",
            "roomid": 0,
            "layerid": 5,
            "stageid": "D003_0"
        }
    ],
    "D003_1": [
        {
            "params1": "FF 02 02 48",
            "params2": "FF 5F FF FF",
            "posx": 2639.282958984375,
            "posy": 0.0,
            "posz": 603.739501953125,
            "anglex": 65535,
            "angley": 49152,
            "anglez": 65535,
            "id": "FC 04",
            "name": "saveObj",
            "extra_info": {
                "scenefid": 72,
                "scenef": "scene flag: 0x8 01",
                "subtype": "dungeon",
                "scen_link": 2,
                "saveobj_name_id": 255,
                "name": "Bird Statue"
            },
            "type": "OBJS",
            "roomid": 0,
            "layerid": 0,
            "stageid": "D003_1"
        }
    ],
    "D003_2": [
        {
            "params1": "FF 03 02 49",
            "params2": "FF 5F FF FF",
            "posx": 2480.139404296875,
            "posy": 0.0,
            "posz": -760.5001831054688,
            "anglex": 65535,
            "angley": 0,
            "anglez": 65535,
            "id": "FC 24",
            "name": "saveObj",
            "extra_info": {
                "scenefid": 73,
                "scenef": "scene flag: 0x8 02",
                "subtype": "dungeon",
                "scen_link": 3,
                "saveobj_name_id": 255,
                "name": "Bird Statue"
            },
            "type": "OBJS",
            "roomid": 0,
            "layerid": 0,
            "stageid": "D003_2"
        }
    ],
    "D003_3": [
        {
            "params1": "FF 03 02 4A",
            "params2": "FF 5F FF FF",
            "posx": -2157.933349609375,
            "posy": 0.0,
            "posz": -552.491455078125,
            "anglex": 65535,
            "angley": 0,
            "anglez": 65535,
            "id": "FC 17",
            "name": "saveObj",
            "extra_info": {
                "scenefid": 74,
                "scenef": "scene flag: 0x8 04",
                "subtype": "dungeon",
                "scen_link": 3,
                "saveobj_name_id": 255,
                "name": "Bird Statue"
            },
            "type": "OBJS",
            "roomid": 0,
            "layerid": 0,
            "stageid": "D003_3"
        }
    ],
    "D003_4": [
        {
            "params1": "FF 02 02 4B",
            "params2": "FF 5F FF FF",
            "posx": 475.9293212890625,
            "posy": 0.0,
            "posz": 2249.338134765625,
            "anglex": 65535,
            "angley": 0,
            "anglez": 65535,
            "id": "FC 2A",
            "name": "saveObj",
            "extra_info": {
                "scenefid": 75,
                "scenef": "scene flag: 0x8 08",
                "subtype": "dungeon",
                "scen_link": 2,
                "saveobj_name_id": 255,
                "name": "Bird Statue"
            },
            "type": "OBJS",
            "roomid": 0,
            "layerid": 0,
            "stageid": "D003_4"
        }
    ],
    "D003_5": [
        {
            "params1": "FF 02 02 4C",
            "params2": "FF 5F FF FF",
            "posx": -677.3712768554688,
            "posy": 0.0,
            "posz": -2867.488037109375,
            "anglex": 65535,
            "angley": 0,
            "anglez": 65535,
            "id": "FC 45",
            "name": "saveObj",
            "extra_info": {
                "scenefid": 76,
                "scenef": "scene flag: 0x8 10",
                "subtype": "dungeon",
                "scen_link": 2,
                "saveobj_name_id": 255,
                "name": "Bird Statue"
            },
            "type": "OBJS",
            "roomid": 0,
            "layerid": 0,
            "stageid": "D003_5"
        }
    ],
    "D003_7": [
        {
            "params1": "FF 02 02 4E",
            "params2": "FF 5F FF FF",
            "posx": -621.9866943359375,
            "posy": 0.0,
            "posz": 2150.0,
            "anglex": 65535,
            "angley": 16384,
            "anglez": 65535,
            "id": "FC 06",
            "name": "saveObj",
            "extra_info": {
                "scenefid": 78,
                "scenef": "scene flag: 0x8 40",
                "subtype": "dungeon",
                "scen_link": 2,
                "saveobj_name_id": 255,
                "name": "Bird Statue"
            },
            "type": "OBJS",
            "roomid": 0,
            "layerid": 0,
            "stageid": "D003_7"
        }
    ],
    "D100": [
        {
            "params1": "FF 02 02 60",
            "params2": "FF 5F FF FF",
            "posx": 268.0,
            "posy": 1124.35009765625,
            "posz": 6180.0,
            "anglex": 65535,
            "angley": 58981,
            "anglez": 65535,
            "id": "FC 1D",
            "name": "saveObj",
            "extra_info": {
                "scenefid": 96,
                "scenef": "scene flag: 0xD 01",
                "subtype": "dungeon",
                "scen_link": 2,
                "saveobj_name_id": 255,
                "name": "Bird Statue"
            },
            "type": "OBJS",
            "roomid": 0,
            "layerid": 0,
            "stageid": "D100"
        },
        {
            "params1": "FF 00 02 25",
            "params2": "FF 5F FF FF",
            "posx": 680.0,
            "posy": 0.0,
            "posz": 1560.0,
            "anglex": 65535,
            "angley": 56525,
            "anglez": 65535,
            "id": "FC 24",
            "name": "saveObj",
            "extra_info": {
                "scenefid": 37,
                "scenef": "scene flag: 0x5 20",
                "subtype": "dungeon",
                "scen_link": 0,
                "saveobj_name_id": 255,
                "name": "Bird Statue"
            },
            "type": "OBJS",
            "roomid": 2,
            "layerid": 0,
            "stageid": "D100"
        },
        {
            "params1": "FF 00 02 26",
            "params2": "FF 5F FF FF",
            "posx": -3500.0,
            "posy": 0.0,
            "posz": -8400.0,
            "anglex": 65535,
            "angley": 16384,
            "anglez": 65535,
            "id": "FC 2C",
            "name": "saveObj",
            "extra_info": {
                "scenefid": 38,
                "scenef": "scene flag: 0x5 40",
                "subtype": "dungeon",
                "scen_link": 0,
                "saveobj_name_id": 255,
                "name": "Bird Statue"
            },
            "type": "OBJS",
            "roomid": 5,
            "layerid": 0,
            "stageid": "D100"
        },
        {
            "params1": "FF 00 02 27",
            "params2": "FF 5F FF FF",
            "posx": 1027.0,
            "posy": 300.0,
            "posz": -16994.0,
            "anglex": 65535,
            "angley": 63716,
            "anglez": 65535,
            "id": "FC 18",
            "name": "saveObj",
            "extra_info": {
                "scenefid": 39,
                "scenef": "scene flag: 0x5 80",
                "subtype": "dungeon",
                "scen_link": 0,
                "saveobj_name_id": 255,
                "name": "Bird Statue"
            },
            "type": "OBJS",
            "roomid": 9,
            "layerid": 0,
            "stageid": "D100"
        }
    ],
    "D101": [
        {
            "params1": "FF 02 02 51",
            "params2": "FF 5F FF FF",
            "posx": -424.2532958984375,
            "posy": 0.0,
            "posz": 5026.220703125,
            "anglex": 65535,
            "angley": 32768,
            "anglez": 65535,
            "id": "FC 3A",
            "name": "saveObj",
            "extra_info": {
                "scenefid": 81,
                "scenef": "scene flag: 0xB 02",
                "subtype": "dungeon",
                "scen_link": 2,
                "saveobj_name_id": 255,
                "name": "Bird Statue"
            },
            "type": "OBJS",
            "roomid": 0,
            "layerid": 0,
            "stageid": "D101"
        },
        {
            "params1": "FF 02 02 50",
            "params2": "FF 5F FF FF",
            "posx": 386.0598449707031,
            "posy": 7569.6103515625,
            "posz": 1385.1180419921875,
            "anglex": 65535,
            "angley": 32768,
            "anglez": 65535,
            "id": "FC 58",
            "name": "saveObj",
            "extra_info": {
                "scenefid": 80,
                "scenef": "scene flag: 0xB 01",
                "subtype": "dungeon",
                "scen_link": 2,
                "saveobj_name_id": 255,
                "name": "Bird Statue"
            },
            "type": "OBJS",
            "roomid": 0,
            "layerid": 0,
            "stageid": "D101"
        },
        {
            "params1": "FF 02 02 53",
            "params2": "FF 5F FF FF",
            "posx": -3990.565185546875,
            "posy": 1000.0,
            "posz": 2850.957275390625,
            "anglex": 65535,
            "angley": 24576,
            "anglez": 65535,
            "id": "FC 63",
            "name": "saveObj",
            "extra_info": {
                "scenefid": 83,
                "scenef": "scene flag: 0xB 08",
                "subtype": "dungeon",
                "scen_link": 2,
                "saveobj_name_id": 255,
                "name": "Bird Statue"
            },
            "type": "OBJS",
            "roomid": 0,
            "layerid": 0,
            "stageid": "D101"
        },
        {
            "params1": "FF 01 02 52",
            "params2": "FF 5F FF FF",
            "posx": -12300.0,
            "posy": 1481.52001953125,
            "posz": 1370.0,
            "anglex": 65535,
            "angley": 49152,
            "anglez": 65535,
            "id": "FC 3A",
            "name": "saveObj",
            "extra_info": {
                "scenefid": 82,
                "scenef": "scene flag: 0xB 04",
                "subtype": "dungeon",
                "scen_link": 1,
                "saveobj_name_id": 255,
                "name": "Bird Statue"
            },
            "type": "OBJS",
            "roomid": 3,
            "layerid": 5,
            "stageid": "D101"
        },
        {
            "params1": "FF 02 02 52",
            "params2": "FF 5F FF FF",
            "posx": -5263.140625,
            "posy": -3410.026123046875,
            "posz": 4381.65380859375,
            "anglex": 65535,
            "angley": 14017,
            "anglez": 65535,
            "id": "FC 61",
            "name": "saveObj",
            "extra_info": {
                "scenefid": 82,
                "scenef": "scene flag: 0xB 04",
                "subtype": "dungeon",
                "scen_link": 2,
                "saveobj_name_id": 255,
                "name": "Bird Statue"
            },
            "type": "OBJS",
            "roomid": 4,
            "layerid": 0,
            "stageid": "D101"
        },
        {
            "params1": "FF 02 02 53",
            "params2": "FF 5F FF FF",
            "posx": -3459.30078125,
            "posy": -4218.52001953125,
            "posz": 887.1654052734375,
            "anglex": 65535,
            "angley": 57344,
            "anglez": 65535,
            "id": "FC B3",
            "name": "saveObj",
            "extra_info": {
                "scenefid": 83,
                "scenef": "scene flag: 0xB 08",
                "subtype": "dungeon",
                "scen_link": 2,
                "saveobj_name_id": 255,
                "name": "Bird Statue"
            },
            "type": "OBJS",
            "roomid": 4,
            "layerid": 5,
            "stageid": "D101"
        },
        {
            "params1": "FF 00 02 54",
            "params2": "FF 5F FF FF",
            "posx": 444.9330749511719,
            "posy": 1000.0,
            "posz": -5435.51220703125,
            "anglex": 65535,
            "angley": 32768,
            "anglez": 65535,
            "id": "10 20",
            "name": "saveObj",
            "extra_info": {
                "scenefid": 84,
                "scenef": "scene flag: 0xB 10",
                "subtype": "dungeon",
                "scen_link": 0,
                "saveobj_name_id": 255,
                "name": "Bird Statue",
                "viewclip_index": 4
            },
            "type": "OBJS",
            "roomid": 5,
            "layerid": 0,
            "stageid": "D101"
        }
    ],
    "D200": [
        {
            "params1": "FF 01 02 34",
            "params2": "FF 5F FF FF",
            "posx": 1000.0,
            "posy": 0.0,
            "posz": -70.0,
            "anglex": 65535,
            "angley": 49152,
            "anglez": 65535,
            "id": "0C 57",
            "name": "saveObj",
            "extra_info": {
                "scenefid": 52,
                "scenef": "scene flag: 0x7 10",
                "subtype": "dungeon",
                "scen_link": 1,
                "saveobj_name_id": 255,
                "name": "Bird Statue",
                "viewclip_index": 3
            },
            "type": "OBJS",
            "roomid": 1,
            "layerid": 0,
            "stageid": "D200"
        },
        {
            "params1": "FF 01 02 30",
            "params2": "FF 5F FF FF",
            "posx": 800.0,
            "posy": 0.0,
            "posz": 14200.0,
            "anglex": 65535,
            "angley": 52793,
            "anglez": 65535,
            "id": "04 5C",
            "name": "saveObj",
            "extra_info": {
                "scenefid": 48,
                "scenef": "scene flag: 0x7 01",
                "subtype": "dungeon",
                "scen_link": 1,
                "saveobj_name_id": 255,
                "name": "Bird Statue",
                "viewclip_index": 1
            },
            "type": "OBJS",
            "roomid": 1,
            "layerid": 0,
            "stageid": "D200"
        },
        {
            "params1": "FF 00 02 32",
            "params2": "FF 5F FF FF",
            "posx": 9100.0,
            "posy": 450.0,
            "posz": -4500.0,
            "anglex": 65535,
            "angley": 19114,
            "anglez": 65535,
            "id": "1C 01",
            "name": "saveObj",
            "extra_info": {
                "scenefid": 50,
                "scenef": "scene flag: 0x7 04",
                "subtype": "dungeon",
                "scen_link": 0,
                "saveobj_name_id": 255,
                "name": "Bird Statue",
                "viewclip_index": 7
            },
            "type": "OBJS",
            "roomid": 2,
            "layerid": 0,
            "stageid": "D200"
        },
        {
            "params1": "FF 02 02 35",
            "params2": "FF 5F FF FF",
            "posx": -9600.0,
            "posy": 6050.0,
            "posz": -13840.0,
            "anglex": 65535,
            "angley": 16384,
            "anglez": 65535,
            "id": "FC 41",
            "name": "saveObj",
            "extra_info": {
                "scenefid": 53,
                "scenef": "scene flag: 0x7 20",
                "subtype": "dungeon",
                "scen_link": 2,
                "saveobj_name_id": 255,
                "name": "Bird Statue"
            },
            "type": "OBJS",
            "roomid": 4,
            "layerid": 0,
            "stageid": "D200"
        }
    ],
    "D201": [
        {
            "params1": "FF 01 02 00",
            "params2": "FF 5F FF FF",
            "posx": 1282.2440185546875,
            "posy": 1100.0,
            "posz": 5974.70556640625,
            "anglex": 65535,
            "angley": 49152,
            "anglez": 65535,
            "id": "FC 18",
            "name": "saveObj",
            "extra_info": {
                "scenefid": 0,
                "scenef": "scene flag: 0x1 01",
                "subtype": "dungeon",
                "scen_link": 1,
                "saveobj_name_id": 255,
                "name": "Bird Statue"
            },
            "type": "OBJS",
            "roomid": 0,
            "layerid": 0,
            "stageid": "D201"
        },
        {
            "params1": "FF 00 02 12",
            "params2": "FF 5F FF FF",
            "posx": 4050.0,
            "posy": 0.005890000145882368,
            "posz": -5132.7119140625,
            "anglex": 65535,
            "angley": 0,
            "anglez": 65535,
            "id": "FC 02",
            "name": "saveObj",
            "extra_info": {
                "scenefid": 18,
                "scenef": "scene flag: 0x3 04",
                "subtype": "dungeon",
                "scen_link": 0,
                "saveobj_name_id": 255,
                "name": "Bird Statue"
            },
            "type": "OBJS",
            "roomid": 1,
            "layerid": 0,
            "stageid": "D201"
        },
        {
            "params1": "FF 02 02 22",
            "params2": "FF 5F FF FF",
            "posx": -7008.55517578125,
            "posy": 0.0,
            "posz": -15921.748046875,
            "anglex": 65535,
            "angley": 49152,
            "anglez": 65535,
            "id": "FC 59",
            "name": "saveObj",
            "extra_info": {
                "scenefid": 34,
                "scenef": "scene flag: 0x5 04",
                "subtype": "dungeon",
                "scen_link": 2,
                "saveobj_name_id": 255,
                "name": "Bird Statue"
            },
            "type": "OBJS",
            "roomid": 3,
            "layerid": 0,
            "stageid": "D201"
        },
        {
            "params1": "FF 01 02 13",
            "params2": "FF 5F FF FF",
            "posx": -7581.22119140625,
            "posy": -550.0,
            "posz": -11476.7080078125,
            "anglex": 65535,
            "angley": 8192,
            "anglez": 65535,
            "id": "FC 03",
            "name": "saveObj",
            "extra_info": {
                "scenefid": 19,
                "scenef": "scene flag: 0x3 08",
                "subtype": "dungeon",
                "scen_link": 1,
                "saveobj_name_id": 255,
                "name": "Bird Statue"
            },
            "type": "OBJS",
            "roomid": 5,
            "layerid": 0,
            "stageid": "D201"
        },
        {
            "params1": "FF 02 02 4C",
            "params2": "FF 5F FF FF",
            "posx": 0.0,
            "posy": 1100.0,
            "posz": -1099.999267578125,
            "anglex": 65535,
            "angley": 0,
            "anglez": 65535,
            "id": "FC 05",
            "name": "saveObj",
            "extra_info": {
                "scenefid": 76,
                "scenef": "scene flag: 0x8 10",
                "subtype": "dungeon",
                "scen_link": 2,
                "saveobj_name_id": 255,
                "name": "Bird Statue"
            },
            "type": "OBJS",
            "roomid": 6,
            "layerid": 0,
            "stageid": "D201"
        },
        {
            "params1": "FF FF 02 46",
            "params2": "FF 5F FF FF",
            "posx": -11594.13671875,
            "posy": 600.0,
            "posz": -10016.7646484375,
            "anglex": 65535,
            "angley": 0,
            "anglez": 65535,
            "id": "FC 00",
            "name": "saveObj",
            "extra_info": {
                "scenefid": 70,
                "scenef": "scene flag: 0x9 40",
                "subtype": "dungeon",
                "scen_link": 255,
                "saveobj_name_id": 255,
                "name": "Bird Statue"
            },
            "type": "OBJS",
            "roomid": 7,
            "layerid": 0,
            "stageid": "D201"
        },
        {
            "params1": "02 03 01 72",
            "params2": "FF 5F FF 0F",
            "posx": 0.0,
            "posy": -550.0,
            "posz": -14250.0,
            "anglex": 65535,
            "angley": 0,
            "anglez": 65535,
            "id": "FC 0A",
            "name": "saveObj",
            "extra_info": {
                "scenefid": 114,
                "scenef": "scene flag: 0xF 04",
                "subtype": "overworld",
                "scen_link": 3,
                "saveobj_name_id": 15,
                "name": "Inside Fire Sanctuary"
            },
            "type": "OBJS",
            "roomid": 10,
            "layerid": 0,
            "stageid": "D201"
        }
    ],
    "D201_1": [
        {
            "params1": "FF FF 02 00",
            "params2": "FF 5F FF FF",
            "posx": 1282.2440185546875,
            "posy": 1100.0,
            "posz": 5974.70556640625,
            "anglex": 65535,
            "angley": 49152,
            "anglez": 65535,
            "id": "FC 01",
            "name": "saveObj",
            "extra_info": {
                "scenefid": 0,
                "scenef": "scene flag: 0x1 01",
                "subtype": "dungeon",
                "scen_link": 255,
                "saveobj_name_id": 255,
                "name": "Bird Statue"
            },
            "type": "OBJS",
            "roomid": 0,
            "layerid": 0,
            "stageid": "D201_1"
        },
        {
            "params1": "FF 00 02 12",
            "params2": "FF 5F FF FF",
            "posx": 3200.0,
            "posy": 200.0,
            "posz": -5001.3974609375,
            "anglex": 65535,
            "angley": 16384,
            "anglez": 65535,
            "id": "FC 15",
            "name": "saveObj",
            "extra_info": {
                "scenefid": 18,
                "scenef": "scene flag: 0x3 04",
                "subtype": "dungeon",
                "scen_link": 0,
                "saveobj_name_id": 255,
                "name": "Bird Statue"
            },
            "type": "OBJS",
            "roomid": 1,
            "layerid": 0,
            "stageid": "D201_1"
        },
        {
            "params1": "FF FF 02 22",
            "params2": "FF 5F FF FF",
            "posx": -7017.24951171875,
            "posy": 0.0,
            "posz": -16000.361328125,
            "anglex": 65535,
            "angley": 49152,
            "anglez": 65535,
            "id": "FC 00",
            "name": "saveObj",
            "extra_info": {
                "scenefid": 34,
                "scenef": "scene flag: 0x5 04",
                "subtype": "dungeon",
                "scen_link": 255,
                "saveobj_name_id": 255,
                "name": "Bird Statue"
            },
            "type": "OBJS",
            "roomid": 3,
            "layerid": 0,
            "stageid": "D201_1"
        },
        {
            "params1": "FF 03 02 13",
            "params2": "FF 5F FF FF",
            "posx": -7581.22119140625,
            "posy": -550.0,
            "posz": -11476.7080078125,
            "anglex": 65535,
            "angley": 8192,
            "anglez": 65535,
            "id": "FC 1F",
            "name": "saveObj",
            "extra_info": {
                "scenefid": 19,
                "scenef": "scene flag: 0x3 08",
                "subtype": "dungeon",
                "scen_link": 3,
                "saveobj_name_id": 255,
                "name": "Bird Statue"
            },
            "type": "OBJS",
            "roomid": 5,
            "layerid": 0,
            "stageid": "D201_1"
        },
        {
            "params1": "FF 02 02 4C",
            "params2": "FF 5F FF FF",
            "posx": -222.76132202148438,
            "posy": 1100.0,
            "posz": -1072.9979248046875,
            "anglex": 65535,
            "angley": 8192,
            "anglez": 65535,
            "id": "FC 11",
            "name": "saveObj",
            "extra_info": {
                "scenefid": 76,
                "scenef": "scene flag: 0x8 10",
                "subtype": "dungeon",
                "scen_link": 2,
                "saveobj_name_id": 255,
                "name": "Bird Statue"
            },
            "type": "OBJS",
            "roomid": 6,
            "layerid": 0,
            "stageid": "D201_1"
        },
        {
            "params1": "FF 00 02 46",
            "params2": "FF 5F FF FF",
            "posx": -11594.13671875,
            "posy": 600.0,
            "posz": -10016.7646484375,
            "anglex": 65535,
            "angley": 0,
            "anglez": 65535,
            "id": "FC 05",
            "name": "saveObj",
            "extra_info": {
                "scenefid": 70,
                "scenef": "scene flag: 0x9 40",
                "subtype": "dungeon",
                "scen_link": 0,
                "saveobj_name_id": 255,
                "name": "Bird Statue"
            },
            "type": "OBJS",
            "roomid": 7,
            "layerid": 0,
            "stageid": "D201_1"
        },
        {
            "params1": "02 03 01 72",
            "params2": "FF 5F FF 0F",
            "posx": 0.0,
            "posy": -550.0,
            "posz": -14250.0,
            "anglex": 65535,
            "angley": 0,
            "anglez": 65535,
            "id": "FC 03",
            "name": "saveObj",
            "extra_info": {
                "scenefid": 114,
                "scenef": "scene flag: 0xF 04",
                "subtype": "overworld",
                "scen_link": 3,
                "saveobj_name_id": 15,
                "name": "Inside Fire Sanctuary"
            },
            "type": "OBJS",
            "roomid": 10,
            "layerid": 0,
            "stageid": "D201_1"
        }
    ],
    "D300": [
        {
            "params1": "FF 01 02 50",
            "params2": "FF 5F FF FF",
            "posx": -900.0,
            "posy": 0.0,
            "posz": 2200.0,
            "anglex": 65535,
            "angley": 32768,
            "anglez": 65535,
            "id": "FC 23",
            "name": "saveObj",
            "extra_info": {
                "scenefid": 80,
                "scenef": "scene flag: 0xB 01",
                "subtype": "dungeon",
                "scen_link": 1,
                "saveobj_name_id": 255,
                "name": "Bird Statue"
            },
            "type": "OBJS",
            "roomid": 0,
            "layerid": 0,
            "stageid": "D300"
        },
        {
            "params1": "FF 04 02 4C",
            "params2": "FF 5F FF FF",
            "posx": -3745.0,
            "posy": 1100.0,
            "posz": -20750.0,
            "anglex": 65535,
            "angley": 32768,
            "anglez": 65535,
            "id": "FC 02",
            "name": "saveObj",
            "extra_info": {
                "scenefid": 76,
                "scenef": "scene flag: 0x8 10",
                "subtype": "dungeon",
                "scen_link": 4,
                "saveobj_name_id": 255,
                "name": "Bird Statue"
            },
            "type": "OBJS",
            "roomid": 5,
            "layerid": 0,
            "stageid": "D300"
        },
        {
            "params1": "FF 04 02 56",
            "params2": "FF 5F FF FF",
            "posx": -700.0,
            "posy": 600.0,
            "posz": -8860.0,
            "anglex": 65535,
            "angley": 0,
            "anglez": 65535,
            "id": "FC 03",
            "name": "saveObj",
            "extra_info": {
                "scenefid": 86,
                "scenef": "scene flag: 0xB 40",
                "subtype": "dungeon",
                "scen_link": 4,
                "saveobj_name_id": 255,
                "name": "Bird Statue"
            },
            "type": "OBJS",
            "roomid": 5,
            "layerid": 0,
            "stageid": "D300"
        },
        {
            "params1": "FF 04 02 57",
            "params2": "FF 5F FF FF",
            "posx": 4125.0,
            "posy": 1100.0,
            "posz": -22800.0,
            "anglex": 65535,
            "angley": 0,
            "anglez": 65535,
            "id": "FC 08",
            "name": "saveObj",
            "extra_info": {
                "scenefid": 87,
                "scenef": "scene flag: 0xB 80",
                "subtype": "dungeon",
                "scen_link": 4,
                "saveobj_name_id": 255,
                "name": "Bird Statue"
            },
            "type": "OBJS",
            "roomid": 5,
            "layerid": 0,
            "stageid": "D300"
        }
    ],
    "D300_1": [
        {
            "params1": "FF 01 02 50",
            "params2": "FF 5F FF FF",
            "posx": -900.0,
            "posy": 0.0,
            "posz": 2200.0,
            "anglex": 65535,
            "angley": 32768,
            "anglez": 65535,
            "id": "FC 01",
            "name": "saveObj",
            "extra_info": {
                "scenefid": 80,
                "scenef": "scene flag: 0xB 01",
                "subtype": "dungeon",
                "scen_link": 1,
                "saveobj_name_id": 255,
                "name": "Bird Statue"
            },
            "type": "OBJS",
            "roomid": 0,
            "layerid": 0,
            "stageid": "D300_1"
        },
        {
            "params1": "FF 04 02 4C",
            "params2": "FF 5F FF FF",
            "posx": -3745.0,
            "posy": 1100.0,
            "posz": -20730.0,
            "anglex": 65535,
            "angley": 32768,
            "anglez": 65535,
            "id": "FC 16",
            "name": "saveObj",
            "extra_info": {
                "scenefid": 76,
                "scenef": "scene flag: 0x8 10",
                "subtype": "dungeon",
                "scen_link": 4,
                "saveobj_name_id": 255,
                "name": "Bird Statue"
            },
            "type": "OBJS",
            "roomid": 5,
            "layerid": 0,
            "stageid": "D300_1"
        },
        {
            "params1": "FF 04 02 56",
            "params2": "FF 5F FF FF",
            "posx": -700.0,
            "posy": 600.0,
            "posz": -8860.0,
            "anglex": 65535,
            "angley": 0,
            "anglez": 65535,
            "id": "FC 1A",
            "name": "saveObj",
            "extra_info": {
                "scenefid": 86,
                "scenef": "scene flag: 0xB 40",
                "subtype": "dungeon",
                "scen_link": 4,
                "saveobj_name_id": 255,
                "name": "Bird Statue"
            },
            "type": "OBJS",
            "roomid": 5,
            "layerid": 0,
            "stageid": "D300_1"
        },
        {
            "params1": "FF 04 02 57",
            "params2": "FF 5F FF FF",
            "posx": 4125.0,
            "posy": 1100.0,
            "posz": -22800.0,
            "anglex": 65535,
            "angley": 0,
            "anglez": 65535,
            "id": "FC 6C",
            "name": "saveObj",
            "extra_info": {
                "scenefid": 87,
                "scenef": "scene flag: 0xB 80",
                "subtype": "dungeon",
                "scen_link": 4,
                "saveobj_name_id": 255,
                "name": "Bird Statue"
            },
            "type": "OBJS",
            "roomid": 5,
            "layerid": 0,
            "stageid": "D300_1"
        }
    ],
    "D301": [
        {
            "params1": "FF 02 02 4A",
            "params2": "FF 5F FF FF",
            "posx": -4993.13818359375,
            "posy": 0.0,
            "posz": 811.5470581054688,
            "anglex": 65535,
            "angley": 16384,
            "anglez": 65535,
            "id": "FC 00",
            "name": "saveObj",
            "extra_info": {
                "scenefid": 74,
                "scenef": "scene flag: 0x8 04",
                "subtype": "dungeon",
                "scen_link": 2,
                "saveobj_name_id": 255,
                "name": "Bird Statue"
            },
            "type": "OBJS",
            "roomid": 1,
            "layerid": 0,
            "stageid": "D301"
        },
        {
            "params1": "FF 01 02 48",
            "params2": "FF 5F FF FF",
            "posx": -2766.865966796875,
            "posy": -1600.0,
            "posz": 1830.2725830078125,
            "anglex": 65535,
            "angley": 16384,
            "anglez": 65535,
            "id": "24 05",
            "name": "saveObj",
            "extra_info": {
                "scenefid": 72,
                "scenef": "scene flag: 0x8 01",
                "subtype": "dungeon",
                "scen_link": 1,
                "saveobj_name_id": 255,
                "name": "Bird Statue",
                "viewclip_index": 9
            },
            "type": "OBJS",
            "roomid": 9,
            "layerid": 0,
            "stageid": "D301"
        },
        {
            "params1": "FF 00 02 47",
            "params2": "FF 5F FF FF",
            "posx": 4818.77197265625,
            "posy": 0.0,
            "posz": -730.9542846679688,
            "anglex": 65535,
            "angley": 49152,
            "anglez": 65535,
            "id": "FC 01",
            "name": "saveObj",
            "extra_info": {
                "scenefid": 71,
                "scenef": "scene flag: 0x9 80",
                "subtype": "dungeon",
                "scen_link": 0,
                "saveobj_name_id": 255,
                "name": "Bird Statue"
            },
            "type": "OBJS",
            "roomid": 13,
            "layerid": 0,
            "stageid": "D301"
        }
    ],
    "F000": [
        {
            "params1": "FF FF 00 2E",
            "params2": "FF 5F FF FF",
            "posx": -4698.884765625,
            "posy": 1237.6900634765625,
            "posz": -6364.4482421875,
            "anglex": 65535,
            "angley": 36956,
            "anglez": 65535,
            "id": "FC 31",
            "name": "saveObj",
            "extra_info": {
                "scenefid": 46,
                "scenef": "scene flag: 0x4 40",
                "subtype": "normal",
                "scen_link": 255,
                "saveobj_name_id": 255,
                "name": "Bird Statue"
            },
            "type": "OBJS",
            "roomid": 0,
            "layerid": 0,
            "stageid": "F000"
        },
        {
            "params1": "FF FF 00 2F",
            "params2": "FF 5F FF FF",
            "posx": 2186.927734375,
            "posy": 393.760009765625,
            "posz": 804.235107421875,
            "anglex": 65535,
            "angley": 728,
            "anglez": 65535,
            "id": "FC 32",
            "name": "saveObj",
            "extra_info": {
                "scenefid": 47,
                "scenef": "scene flag: 0x4 80",
                "subtype": "normal",
                "scen_link": 255,
                "saveobj_name_id": 255,
                "name": "Bird Statue"
            },
            "type": "OBJS",
            "roomid": 0,
            "layerid": 0,
            "stageid": "F000"
        },
        {
            "params1": "FF FF 00 30",
            "params2": "FF 5F FF FF",
            "posx": 4174.2197265625,
            "posy": -3157.320068359375,
            "posz": -5928.22119140625,
            "anglex": 65535,
            "angley": 11468,
            "anglez": 65534,
            "id": "FC 33",
            "name": "saveObj",
            "extra_info": {
                "scenefid": 48,
                "scenef": "scene flag: 0x7 01",
                "subtype": "normal",
                "scen_link": 255,
                "saveobj_name_id": 255,
                "name": "Bird Statue"
            },
            "type": "OBJS",
            "roomid": 0,
            "layerid": 0,
            "stageid": "F000"
        },
        {
            "params1": "FF FF 00 31",
            "params2": "FF 5F FF FF",
            "posx": -2353.656005859375,
            "posy": 1880.570068359375,
            "posz": -9622.822265625,
            "anglex": 65535,
            "angley": 182,
            "anglez": 65535,
            "id": "FC 34",
            "name": "saveObj",
            "extra_info": {
                "scenefid": 49,
                "scenef": "scene flag: 0x7 02",
                "subtype": "normal",
                "scen_link": 255,
                "saveobj_name_id": 255,
                "name": "Bird Statue"
            },
            "type": "OBJS",
            "roomid": 0,
            "layerid": 0,
            "stageid": "F000"
        }
    ],
    "F010r": [
        {
            "params1": "FF FF 00 35",
            "params2": "FF 5F FF FF",
            "posx": -179.46446228027344,
            "posy": 395.57000732421875,
            "posz": 4651.8583984375,
            "anglex": 65535,
            "angley": 32768,
            "anglez": 65535,
            "id": "FC 01",
            "name": "saveObj",
            "extra_info": {
                "scenefid": 53,
                "scenef": "scene flag: 0x7 20",
                "subtype": "normal",
                "scen_link": 255,
                "saveobj_name_id": 255,
                "name": "Bird Statue"
            },
            "type": "OBJS",
            "roomid": 0,
            "layerid": 0,
            "stageid": "F010r"
        }
    ],
    "F020": [
        {
            "params1": "FF FF 00 20",
            "params2": "FF 5F FF FF",
            "posx": 102115.7734375,
            "posy": -10643.59375,
            "posz": 47017.1640625,
            "anglex": 65535,
            "angley": 0,
            "anglez": 65535,
            "id": "FC 6E",
            "name": "saveObj",
            "extra_info": {
                "scenefid": 32,
                "scenef": "scene flag: 0x5 01",
                "subtype": "normal",
                "scen_link": 255,
                "saveobj_name_id": 255,
                "name": "Bird Statue"
            },
            "type": "OBJS",
            "roomid": 0,
            "layerid": 0,
            "stageid": "F020"
        }
    ],
    "F100": [
        {
            "params1": "01 0A 01 64",
            "params2": "FF 5F FF 01",
            "posx": -8360.0,
            "posy": -930.0,
            "posz": -1620.0,
            "anglex": 800,
            "angley": 38594,
            "anglez": 65535,
            "id": "60 7B",
            "name": "saveObj",
            "extra_info": {
                "scenefid": 100,
                "scenef": "scene flag: 0xD 10",
                "subtype": "overworld",
                "scen_link": 10,
                "saveobj_name_id": 1,
                "name": "Faron Woods Entry",
                "viewclip_index": 24
            },
            "type": "OBJS",
            "roomid": 0,
            "layerid": 0,
            "stageid": "F100"
        },
        {
            "params1": "01 0A 01 65",
            "params2": "FF 5F FF 02",
            "posx": -2200.0,
            "posy": -500.0,
            "posz": 5450.0,
            "anglex": 801,
            "angley": 49335,
            "anglez": 65535,
            "id": "00 7C",
            "name": "saveObj",
            "extra_info": {
                "scenefid": 101,
                "scenef": "scene flag: 0xD 20",
                "subtype": "overworld",
                "scen_link": 10,
                "saveobj_name_id": 2,
                "name": "In the Woods",
                "viewclip_index": 0
            },
            "type": "OBJS",
            "roomid": 0,
            "layerid": 0,
            "stageid": "F100"
        },
        {
            "params1": "01 0A 01 66",
            "params2": "FF 5F FF 03",
            "posx": 7260.0,
            "posy": 2100.0,
            "posz": -9375.0,
            "anglex": 802,
            "angley": 20024,
            "anglez": 65535,
            "id": "44 7D",
            "name": "saveObj",
            "extra_info": {
                "scenefid": 102,
                "scenef": "scene flag: 0xD 40",
                "subtype": "overworld",
                "scen_link": 10,
                "saveobj_name_id": 3,
                "name": "Viewing Platform",
                "viewclip_index": 17
            },
            "type": "OBJS",
            "roomid": 0,
            "layerid": 0,
            "stageid": "F100"
        },
        {
            "params1": "01 0A 01 69",
            "params2": "FF 5F FF 04",
            "posx": -1180.0,
            "posy": 4979.4501953125,
            "posz": -4280.0,
            "anglex": 803,
            "angley": 16384,
            "anglez": 65535,
            "id": "FC 7E",
            "name": "saveObj",
            "extra_info": {
                "scenefid": 105,
                "scenef": "scene flag: 0xC 02",
                "subtype": "overworld",
                "scen_link": 10,
                "saveobj_name_id": 4,
                "name": "The Great Tree"
            },
            "type": "OBJS",
            "roomid": 0,
            "layerid": 0,
            "stageid": "F100"
        }
    ],
    "F101": [
        {
            "params1": "01 02 01 67",
            "params2": "FF 5F FF 06",
            "posx": 2350.0,
            "posy": 1543.17333984375,
            "posz": 10250.0,
            "anglex": 65535,
            "angley": 3640,
            "anglez": 65535,
            "id": "FC 44",
            "name": "saveObj",
            "extra_info": {
                "scenefid": 103,
                "scenef": "scene flag: 0xD 80",
                "subtype": "overworld",
                "scen_link": 2,
                "saveobj_name_id": 6,
                "name": "Deep Woods"
            },
            "type": "OBJS",
            "roomid": 0,
            "layerid": 0,
            "stageid": "F101"
        },
        {
            "params1": "01 02 01 68",
            "params2": "FF 5F FF 05",
            "posx": -765.0,
            "posy": 757.9931030273438,
            "posz": 3350.0,
            "anglex": 65535,
            "angley": 0,
            "anglez": 65535,
            "id": "FC 45",
            "name": "saveObj",
            "extra_info": {
                "scenefid": 104,
                "scenef": "scene flag: 0xC 01",
                "subtype": "overworld",
                "scen_link": 2,
                "saveobj_name_id": 5,
                "name": "Forest Temple"
            },
            "type": "OBJS",
            "roomid": 0,
            "layerid": 0,
            "stageid": "F101"
        }
    ],
    "F102": [
        {
            "params1": "FF FF 00 22",
            "params2": "FF 5F FF FF",
            "posx": 1110.0,
            "posy": -824.6444702148438,
            "posz": 15400.0,
            "anglex": 65535,
            "angley": 57344,
            "anglez": 65535,
            "id": "08 01",
            "name": "saveObj",
            "extra_info": {
                "scenefid": 34,
                "scenef": "scene flag: 0x5 04",
                "subtype": "normal",
                "scen_link": 255,
                "saveobj_name_id": 255,
                "name": "Bird Statue",
                "viewclip_index": 2
            },
            "type": "OBJS",
            "roomid": 2,
            "layerid": 0,
            "stageid": "F102"
        },
        {
            "params1": "01 00 01 20",
            "params2": "FF 5F FF 07",
            "posx": 2660.0,
            "posy": 433.50311279296875,
            "posz": 8110.0,
            "anglex": 65535,
            "angley": 62806,
            "anglez": 65535,
            "id": "0C 07",
            "name": "saveObj",
            "extra_info": {
                "scenefid": 32,
                "scenef": "scene flag: 0x5 01",
                "subtype": "overworld",
                "scen_link": 0,
                "saveobj_name_id": 7,
                "name": "Lake Floria",
                "viewclip_index": 3
            },
            "type": "OBJS",
            "roomid": 3,
            "layerid": 0,
            "stageid": "F102"
        },
        {
            "params1": "FF FF 01 21",
            "params2": "FF 5F FF 08",
            "posx": -4950.0,
            "posy": 249.05262756347656,
            "posz": -5700.0,
            "anglex": 65535,
            "angley": 12743,
            "anglez": 65535,
            "id": "10 1E",
            "name": "saveObj",
            "extra_info": {
                "scenefid": 33,
                "scenef": "scene flag: 0x5 02",
                "subtype": "overworld",
                "scen_link": 255,
                "saveobj_name_id": 8,
                "name": "Floria Waterfall",
                "viewclip_index": 4
            },
            "type": "OBJS",
            "roomid": 4,
            "layerid": 0,
            "stageid": "F102"
        }
    ],
    "F102_1": [
        {
            "params1": "01 03 01 21",
            "params2": "FF 5F FF 08",
            "posx": -4950.0,
            "posy": 249.05262756347656,
            "posz": -5700.0,
            "anglex": 65535,
            "angley": 12743,
            "anglez": 65535,
            "id": "FC 03",
            "name": "saveObj",
            "extra_info": {
                "scenefid": 33,
                "scenef": "scene flag: 0x5 02",
                "subtype": "overworld",
                "scen_link": 3,
                "saveobj_name_id": 8,
                "name": "Floria Waterfall"
            },
            "type": "OBJS",
            "roomid": 0,
            "layerid": 0,
            "stageid": "F102_1"
        },
        {
            "params1": "FF FF 00 22",
            "params2": "FF 5F FF FF",
            "posx": 1110.0,
            "posy": -824.6444702148438,
            "posz": 15400.0,
            "anglex": 65535,
            "angley": 57344,
            "anglez": 65535,
            "id": "FC 48",
            "name": "saveObj",
            "extra_info": {
                "scenefid": 34,
                "scenef": "scene flag: 0x5 04",
                "subtype": "normal",
                "scen_link": 255,
                "saveobj_name_id": 255,
                "name": "Bird Statue"
            },
            "type": "OBJS",
            "roomid": 0,
            "layerid": 0,
            "stageid": "F102_1"
        },
        {
            "params1": "FF FF 01 20",
            "params2": "FF 5F FF 07",
            "posx": 2660.0,
            "posy": 433.50311279296875,
            "posz": 8110.0,
            "anglex": 65535,
            "angley": 62806,
            "anglez": 65535,
            "id": "FC 49",
            "name": "saveObj",
            "extra_info": {
                "scenefid": 32,
                "scenef": "scene flag: 0x5 01",
                "subtype": "overworld",
                "scen_link": 255,
                "saveobj_name_id": 7,
                "name": "Lake Floria"
            },
            "type": "OBJS",
            "roomid": 0,
            "layerid": 0,
            "stageid": "F102_1"
        }
    ],
    "F102_2": [
        {
            "params1": "FF FF 00 22",
            "params2": "FF 5F FF FF",
            "posx": 1110.0,
            "posy": -824.6444702148438,
            "posz": 15400.0,
            "anglex": 65535,
            "angley": 57344,
            "anglez": 65535,
            "id": "FC 57",
            "name": "saveObj",
            "extra_info": {
                "scenefid": 34,
                "scenef": "scene flag: 0x5 04",
                "subtype": "normal",
                "scen_link": 255,
                "saveobj_name_id": 255,
                "name": "Bird Statue"
            },
            "type": "OBJS",
            "roomid": 0,
            "layerid": 0,
            "stageid": "F102_2"
        },
        {
            "params1": "FF FF 01 20",
            "params2": "FF 5F FF 07",
            "posx": 2660.0,
            "posy": 433.50311279296875,
            "posz": 8110.0,
            "anglex": 65535,
            "angley": 62806,
            "anglez": 65535,
            "id": "FC 58",
            "name": "saveObj",
            "extra_info": {
                "scenefid": 32,
                "scenef": "scene flag: 0x5 01",
                "subtype": "overworld",
                "scen_link": 255,
                "saveobj_name_id": 7,
                "name": "Lake Floria"
            },
            "type": "OBJS",
            "roomid": 0,
            "layerid": 0,
            "stageid": "F102_2"
        },
        {
            "params1": "FF FF 01 21",
            "params2": "FF 5F FF 08",
            "posx": -4950.0,
            "posy": 249.05262756347656,
            "posz": -5700.0,
            "anglex": 65535,
            "angley": 12743,
            "anglez": 65535,
            "id": "FC 59",
            "name": "saveObj",
            "extra_info": {
                "scenefid": 33,
                "scenef": "scene flag: 0x5 02",
                "subtype": "overworld",
                "scen_link": 255,
                "saveobj_name_id": 8,
                "name": "Floria Waterfall"
            },
            "type": "OBJS",
            "roomid": 0,
            "layerid": 0,
            "stageid": "F102_2"
        }
    ],
    "F103": [
        {
            "params1": "01 01 01 FF",
            "params2": "FF 5F FF 09",
            "posx": -1180.0,
            "posy": 4979.4501953125,
            "posz": -4280.0,
            "anglex": 803,
            "angley": 20024,
            "anglez": 65535,
            "id": "FC 7C",
            "name": "saveObj",
            "extra_info": {
                "scenefid": 255,
                "scenef": "no flag",
                "subtype": "overworld",
                "scen_link": 1,
                "saveobj_name_id": 9,
                "name": "Great Tree Top"
            },
            "type": "OBJS",
            "roomid": 0,
            "layerid": 0,
            "stageid": "F103"
        },
        {
            "params1": "01 01 00 FF",
            "params2": "FF 5F FF 01",
            "posx": -8360.0,
            "posy": -930.0,
            "posz": -1620.0,
            "anglex": 800,
            "angley": 38594,
            "anglez": 65535,
            "id": "FC 80",
            "name": "saveObj",
            "extra_info": {
                "scenefid": 255,
                "scenef": "no flag",
                "subtype": "normal",
                "scen_link": 1,
                "saveobj_name_id": 1,
                "name": "Faron Woods Entry"
            },
            "type": "OBJS",
            "roomid": 0,
            "layerid": 0,
            "stageid": "F103"
        },
        {
            "params1": "01 01 00 FF",
            "params2": "FF 5F FF 02",
            "posx": -2200.0,
            "posy": -500.0,
            "posz": 5450.0,
            "anglex": 801,
            "angley": 49335,
            "anglez": 65535,
            "id": "FC 81",
            "name": "saveObj",
            "extra_info": {
                "scenefid": 255,
                "scenef": "no flag",
                "subtype": "normal",
                "scen_link": 1,
                "saveobj_name_id": 2,
                "name": "In the Woods"
            },
            "type": "OBJS",
            "roomid": 0,
            "layerid": 0,
            "stageid": "F103"
        },
        {
            "params1": "01 01 00 FF",
            "params2": "FF 5F FF 03",
            "posx": 7260.0,
            "posy": 2100.0,
            "posz": -9375.0,
            "anglex": 802,
            "angley": 20024,
            "anglez": 65535,
            "id": "FC 82",
            "name": "saveObj",
            "extra_info": {
                "scenefid": 255,
                "scenef": "no flag",
                "subtype": "normal",
                "scen_link": 1,
                "saveobj_name_id": 3,
                "name": "Viewing Platform"
            },
            "type": "OBJS",
            "roomid": 0,
            "layerid": 0,
            "stageid": "F103"
        }
    ],
    "F200": [
        {
            "params1": "02 00 01 FF",
            "params2": "FF 5F FF 0A",
            "posx": -9900.0,
            "posy": 1840.0,
            "posz": 2800.0,
            "anglex": 804,
            "angley": 0,
            "anglez": 65535,
            "id": "FC 04",
            "name": "saveObj",
            "extra_info": {
                "scenefid": 255,
                "scenef": "no flag",
                "subtype": "overworld",
                "scen_link": 0,
                "saveobj_name_id": 10,
                "name": "Volcano Entry"
            },
            "type": "OBJS",
            "roomid": 0,
            "layerid": 0,
            "stageid": "F200"
        },
        {
            "params1": "02 02 01 FF",
            "params2": "FF 5F FF 0B",
            "posx": 3470.0,
            "posy": 987.8651733398438,
            "posz": 6420.0,
            "anglex": 805,
            "angley": 52793,
            "anglez": 65535,
            "id": "FC 21",
            "name": "saveObj",
            "extra_info": {
                "scenefid": 255,
                "scenef": "no flag",
                "subtype": "overworld",
                "scen_link": 2,
                "saveobj_name_id": 11,
                "name": "Volcano East"
            },
            "type": "OBJS",
            "roomid": 2,
            "layerid": 0,
            "stageid": "F200"
        },
        {
            "params1": "02 02 01 FF",
            "params2": "FF 5F FF 0C",
            "posx": 1100.0,
            "posy": 845.5152587890625,
            "posz": -5600.0,
            "anglex": 806,
            "angley": 0,
            "anglez": 65535,
            "id": "FC 38",
            "name": "saveObj",
            "extra_info": {
                "scenefid": 255,
                "scenef": "no flag",
                "subtype": "overworld",
                "scen_link": 2,
                "saveobj_name_id": 12,
                "name": "Volcano Ascent"
            },
            "type": "OBJS",
            "roomid": 2,
            "layerid": 0,
            "stageid": "F200"
        },
        {
            "params1": "02 02 01 FF",
            "params2": "FF 5F FF 0D",
            "posx": 300.0,
            "posy": 13800.0,
            "posz": -24700.0,
            "anglex": 807,
            "angley": 0,
            "anglez": 65535,
            "id": "FC 12",
            "name": "saveObj",
            "extra_info": {
                "scenefid": 255,
                "scenef": "no flag",
                "subtype": "overworld",
                "scen_link": 2,
                "saveobj_name_id": 13,
                "name": "Temple Entrance"
            },
            "type": "OBJS",
            "roomid": 4,
            "layerid": 0,
            "stageid": "F200"
        }
    ],
    "F201_1": [
        {
            "params1": "FF FF 00 75",
            "params2": "FF 5F FF FF",
            "posx": -400.0,
            "posy": 0.0,
            "posz": -700.0,
            "anglex": 65535,
            "angley": 16384,
            "anglez": 65535,
            "id": "FC 10",
            "name": "saveObj",
            "extra_info": {
                "scenefid": 117,
                "scenef": "scene flag: 0xF 20",
                "subtype": "normal",
                "scen_link": 255,
                "saveobj_name_id": 255,
                "name": "Bird Statue"
            },
            "type": "OBJS",
            "roomid": 0,
            "layerid": 0,
            "stageid": "F201_1"
        }
    ],
    "F201_2": [
        {
            "params1": "FF 02 00 75",
            "params2": "FF 5F FF FF",
            "posx": -400.0,
            "posy": 0.0,
            "posz": -700.0,
            "anglex": 65535,
            "angley": 16384,
            "anglez": 65535,
            "id": "FC 12",
            "name": "saveObj",
            "extra_info": {
                "scenefid": 117,
                "scenef": "scene flag: 0xF 20",
                "subtype": "normal",
                "scen_link": 2,
                "saveobj_name_id": 255,
                "name": "Bird Statue"
            },
            "type": "OBJS",
            "roomid": 0,
            "layerid": 0,
            "stageid": "F201_2"
        }
    ],
    "F201_3": [
        {
            "params1": "02 02 01 65",
            "params2": "FF 5F FF 0E",
            "posx": -600.0,
            "posy": -500.0,
            "posz": -10500.0,
            "anglex": 65535,
            "angley": 0,
            "anglez": 65535,
            "id": "FC 0B",
            "name": "saveObj",
            "extra_info": {
                "scenefid": 101,
                "scenef": "scene flag: 0xD 20",
                "subtype": "overworld",
                "scen_link": 2,
                "saveobj_name_id": 14,
                "name": "Inside the Volcano"
            },
            "type": "OBJS",
            "roomid": 0,
            "layerid": 0,
            "stageid": "F201_3"
        }
    ],
    "F202": [
        {
            "params1": "FF FF 00 FF",
            "params2": "FF 5F FF 0A",
            "posx": -9900.0,
            "posy": 1840.0,
            "posz": 2800.0,
            "anglex": 804,
            "angley": 0,
            "anglez": 65535,
            "id": "FC 0A",
            "name": "saveObj",
            "extra_info": {
                "scenefid": 255,
                "scenef": "no flag",
                "subtype": "normal",
                "scen_link": 255,
                "saveobj_name_id": 10,
                "name": "Volcano Entry"
            },
            "type": "OBJS",
            "roomid": 0,
            "layerid": 0,
            "stageid": "F202"
        },
        {
            "params1": "FF FF 00 FF",
            "params2": "FF 5F FF 0B",
            "posx": 3470.0,
            "posy": 987.8651733398438,
            "posz": 6420.0,
            "anglex": 805,
            "angley": 52793,
            "anglez": 65535,
            "id": "FC C6",
            "name": "saveObj",
            "extra_info": {
                "scenefid": 255,
                "scenef": "no flag",
                "subtype": "normal",
                "scen_link": 255,
                "saveobj_name_id": 11,
                "name": "Volcano East"
            },
            "type": "OBJS",
            "roomid": 2,
            "layerid": 0,
            "stageid": "F202"
        },
        {
            "params1": "FF FF 00 FF",
            "params2": "FF 5F FF 0C",
            "posx": 1100.0,
            "posy": 845.5152587890625,
            "posz": -5600.0,
            "anglex": 806,
            "angley": 0,
            "anglez": 65535,
            "id": "00 C8",
            "name": "saveObj",
            "extra_info": {
                "scenefid": 255,
                "scenef": "no flag",
                "subtype": "normal",
                "scen_link": 255,
                "saveobj_name_id": 12,
                "name": "Volcano Ascent",
                "viewclip_index": 0
            },
            "type": "OBJS",
            "roomid": 2,
            "layerid": 0,
            "stageid": "F202"
        },
        {
            "params1": "FF FF 00 FF",
            "params2": "FF 5F FF 0D",
            "posx": 300.0,
            "posy": 13800.0,
            "posz": -24700.0,
            "anglex": 807,
            "angley": 0,
            "anglez": 65535,
            "id": "FC 6A",
            "name": "saveObj",
            "extra_info": {
                "scenefid": 255,
                "scenef": "no flag",
                "subtype": "normal",
                "scen_link": 255,
                "saveobj_name_id": 13,
                "name": "Temple Entrance"
            },
            "type": "OBJS",
            "roomid": 4,
            "layerid": 0,
            "stageid": "F202"
        }
    ],
    "F210": [
        {
            "params1": "FF FF 00 25",
            "params2": "FF 5F FF FF",
            "posx": 1200.0,
            "posy": -7390.0,
            "posz": 1700.0,
            "anglex": 65535,
            "angley": 10012,
            "anglez": 65535,
            "id": "00 04",
            "name": "saveObj",
            "extra_info": {
                "scenefid": 37,
                "scenef": "scene flag: 0x5 20",
                "subtype": "normal",
                "scen_link": 255,
                "saveobj_name_id": 255,
                "name": "Bird Statue",
                "viewclip_index": 0
            },
            "type": "OBJS",
            "roomid": 0,
            "layerid": 0,
            "stageid": "F210"
        }
    ],
    "F300": [
        {
            "params1": "03 06 01 42",
            "params2": "FF 5F FF 11",
            "posx": 1680.0,
            "posy": 1984.0,
            "posz": 18933.0,
            "anglex": 65535,
            "angley": 16384,
            "anglez": 65535,
            "id": "FC 2C",
            "name": "saveObj",
            "extra_info": {
                "scenefid": 66,
                "scenef": "scene flag: 0x9 04",
                "subtype": "overworld",
                "scen_link": 6,
                "saveobj_name_id": 17,
                "name": "Desert Entrance"
            },
            "type": "OBJS",
            "roomid": 0,
            "layerid": 0,
            "stageid": "F300"
        },
        {
            "params1": "03 06 01 43",
            "params2": "FF 5F FF 13",
            "posx": -2117.896240234375,
            "posy": 475.0,
            "posz": -6749.04052734375,
            "anglex": 65535,
            "angley": 51883,
            "anglez": 65535,
            "id": "FC 2D",
            "name": "saveObj",
            "extra_info": {
                "scenefid": 67,
                "scenef": "scene flag: 0x9 08",
                "subtype": "overworld",
                "scen_link": 6,
                "saveobj_name_id": 19,
                "name": "North Desert"
            },
            "type": "OBJS",
            "roomid": 0,
            "layerid": 0,
            "stageid": "F300"
        },
        {
            "params1": "03 02 01 4D",
            "params2": "FF 5F FF 15",
            "posx": -23334.0,
            "posy": 50.0,
            "posz": 749.0,
            "anglex": 65535,
            "angley": 16384,
            "anglez": 65535,
            "id": "FC A8",
            "name": "saveObj",
            "extra_info": {
                "scenefid": 77,
                "scenef": "scene flag: 0x8 20",
                "subtype": "overworld",
                "scen_link": 2,
                "saveobj_name_id": 21,
                "name": "Desert Gorge"
            },
            "type": "OBJS",
            "roomid": 0,
            "layerid": 0,
            "stageid": "F300"
        },
        {
            "params1": "03 02 01 4E",
            "params2": "FF 5F FF 16",
            "posx": -34352.0,
            "posy": 50.0,
            "posz": -4031.0,
            "anglex": 65535,
            "angley": 49152,
            "anglez": 65535,
            "id": "FC A9",
            "name": "saveObj",
            "extra_info": {
                "scenefid": 78,
                "scenef": "scene flag: 0x8 40",
                "subtype": "overworld",
                "scen_link": 2,
                "saveobj_name_id": 22,
                "name": "Temple of Time"
            },
            "type": "OBJS",
            "roomid": 0,
            "layerid": 0,
            "stageid": "F300"
        },
        {
            "params1": "03 06 01 33",
            "params2": "FF 5F FF 12",
            "posx": -14960.0,
            "posy": 80.0,
            "posz": 8300.0,
            "anglex": 65535,
            "angley": 23665,
            "anglez": 65535,
            "id": "FC B3",
            "name": "saveObj",
            "extra_info": {
                "scenefid": 51,
                "scenef": "scene flag: 0x7 08",
                "subtype": "overworld",
                "scen_link": 6,
                "saveobj_name_id": 18,
                "name": "West Desert"
            },
            "type": "OBJS",
            "roomid": 0,
            "layerid": 0,
            "stageid": "F300"
        },
        {
            "params1": "03 06 01 02",
            "params2": "FF 5F FF 14",
            "posx": 9300.0,
            "posy": 226.72801208496094,
            "posz": 10200.0,
            "anglex": 65535,
            "angley": 0,
            "anglez": 65535,
            "id": "FC B7",
            "name": "saveObj",
            "extra_info": {
                "scenefid": 2,
                "scenef": "scene flag: 0x1 04",
                "subtype": "overworld",
                "scen_link": 6,
                "saveobj_name_id": 20,
                "name": "Stone Cache"
            },
            "type": "OBJS",
            "roomid": 0,
            "layerid": 0,
            "stageid": "F300"
        }
    ],
    "F300_1": [
        {
            "params1": "03 00 01 44",
            "params2": "FF 5F FF 10",
            "posx": 10175.3837890625,
            "posy": 2293.86083984375,
            "posz": 35566.421875,
            "anglex": 65535,
            "angley": 10922,
            "anglez": 65535,
            "id": "FC 14",
            "name": "saveObj",
            "extra_info": {
                "scenefid": 68,
                "scenef": "scene flag: 0x9 10",
                "subtype": "overworld",
                "scen_link": 0,
                "saveobj_name_id": 16,
                "name": "Lanayru Mine Entry"
            },
            "type": "OBJS",
            "roomid": 0,
            "layerid": 0,
            "stageid": "F300_1"
        }
    ],
    "F300_4": [
        {
            "params1": "03 02 01 4D",
            "params2": "FF 5F FF 15",
            "posx": -23334.0,
            "posy": 50.0,
            "posz": 749.0,
            "anglex": 65535,
            "angley": 16384,
            "anglez": 65535,
            "id": "FC 01",
            "name": "saveObj",
            "extra_info": {
                "scenefid": 77,
                "scenef": "scene flag: 0x8 20",
                "subtype": "overworld",
                "scen_link": 2,
                "saveobj_name_id": 21,
                "name": "Desert Gorge"
            },
            "type": "OBJS",
            "roomid": 0,
            "layerid": 0,
            "stageid": "F300_4"
        },
        {
            "params1": "03 02 01 4E",
            "params2": "FF 5F FF 16",
            "posx": -34352.0,
            "posy": 50.0,
            "posz": -4031.0,
            "anglex": 65535,
            "angley": 49152,
            "anglez": 65535,
            "id": "FC 14",
            "name": "saveObj",
            "extra_info": {
                "scenefid": 78,
                "scenef": "scene flag: 0x8 40",
                "subtype": "overworld",
                "scen_link": 2,
                "saveobj_name_id": 22,
                "name": "Temple of Time"
            },
            "type": "OBJS",
            "roomid": 0,
            "layerid": 0,
            "stageid": "F300_4"
        },
        {
            "params1": "03 06 01 42",
            "params2": "FF 5F FF 10",
            "posx": 1680.0,
            "posy": 1984.0,
            "posz": 18933.0,
            "anglex": 65535,
            "angley": 16384,
            "anglez": 65535,
            "id": "FC 19",
            "name": "saveObj",
            "extra_info": {
                "scenefid": 66,
                "scenef": "scene flag: 0x9 04",
                "subtype": "overworld",
                "scen_link": 6,
                "saveobj_name_id": 16,
                "name": "Lanayru Mine Entry"
            },
            "type": "OBJS",
            "roomid": 0,
            "layerid": 0,
            "stageid": "F300_4"
        },
        {
            "params1": "03 06 01 43",
            "params2": "FF 5F FF 13",
            "posx": -2054.0,
            "posy": 475.0,
            "posz": -6773.0,
            "anglex": 65535,
            "angley": 52793,
            "anglez": 65535,
            "id": "FC 1A",
            "name": "saveObj",
            "extra_info": {
                "scenefid": 67,
                "scenef": "scene flag: 0x9 08",
                "subtype": "overworld",
                "scen_link": 6,
                "saveobj_name_id": 19,
                "name": "North Desert"
            },
            "type": "OBJS",
            "roomid": 0,
            "layerid": 0,
            "stageid": "F300_4"
        },
        {
            "params1": "03 06 01 33",
            "params2": "FF 5F FF 12",
            "posx": -14960.0,
            "posy": 80.0,
            "posz": 8300.0,
            "anglex": 65535,
            "angley": 23665,
            "anglez": 65535,
            "id": "FC 1B",
            "name": "saveObj",
            "extra_info": {
                "scenefid": 51,
                "scenef": "scene flag: 0x7 08",
                "subtype": "overworld",
                "scen_link": 6,
                "saveobj_name_id": 18,
                "name": "West Desert"
            },
            "type": "OBJS",
            "roomid": 0,
            "layerid": 0,
            "stageid": "F300_4"
        },
        {
            "params1": "03 06 01 02",
            "params2": "FF 5F FF 14",
            "posx": 9300.0,
            "posy": 247.65599060058594,
            "posz": 10200.0,
            "anglex": 65535,
            "angley": 0,
            "anglez": 65535,
            "id": "FC 1C",
            "name": "saveObj",
            "extra_info": {
                "scenefid": 2,
                "scenef": "scene flag: 0x1 04",
                "subtype": "overworld",
                "scen_link": 6,
                "saveobj_name_id": 20,
                "name": "Stone Cache"
            },
            "type": "OBJS",
            "roomid": 0,
            "layerid": 0,
            "stageid": "F300_4"
        }
    ],
    "F301": [
        {
            "params1": "03 03 01 0A",
            "params2": "FF 5F FF 17",
            "posx": 180.58645629882812,
            "posy": 70.0,
            "posz": -410.0475158691406,
            "anglex": 65535,
            "angley": 16384,
            "anglez": 65535,
            "id": "FC 0D",
            "name": "saveObj",
            "extra_info": {
                "scenefid": 10,
                "scenef": "scene flag: 0x0 04",
                "subtype": "overworld",
                "scen_link": 3,
                "saveobj_name_id": 23,
                "name": "Ancient Harbor"
            },
            "type": "OBJS",
            "roomid": 0,
            "layerid": 0,
            "stageid": "F301"
        }
    ],
    "F301_1": [
        {
            "params1": "03 00 01 1C",
            "params2": "FF 5F FF 18",
            "posx": -48573.57421875,
            "posy": -10000.0,
            "posz": 30736.76171875,
            "anglex": 65535,
            "angley": 0,
            "anglez": 65535,
            "id": "FC 4B",
            "name": "saveObj",
            "extra_info": {
                "scenefid": 28,
                "scenef": "scene flag: 0x2 10",
                "subtype": "overworld",
                "scen_link": 0,
                "saveobj_name_id": 24,
                "name": "Skipper's Retreat"
            },
            "type": "OBJS",
            "roomid": 0,
            "layerid": 0,
            "stageid": "F301_1"
        },
        {
            "params1": "03 00 01 55",
            "params2": "FF 5F FF 19",
            "posx": -123230.5546875,
            "posy": -10000.0,
            "posz": 12391.4697265625,
            "anglex": 65535,
            "angley": 0,
            "anglez": 65535,
            "id": "FC 4C",
            "name": "saveObj",
            "extra_info": {
                "scenefid": 85,
                "scenef": "scene flag: 0xB 20",
                "subtype": "overworld",
                "scen_link": 0,
                "saveobj_name_id": 25,
                "name": "Shipyard"
            },
            "type": "OBJS",
            "roomid": 0,
            "layerid": 0,
            "stageid": "F301_1"
        },
        {
            "params1": "03 00 01 54",
            "params2": "FF 5F FF 1A",
            "posx": -121658.9609375,
            "posy": -10000.0,
            "posz": -34290.58203125,
            "anglex": 65535,
            "angley": 0,
            "anglez": 65535,
            "id": "FC 4D",
            "name": "saveObj",
            "extra_info": {
                "scenefid": 84,
                "scenef": "scene flag: 0xB 10",
                "subtype": "overworld",
                "scen_link": 0,
                "saveobj_name_id": 26,
                "name": "Pirate Stronghold"
            },
            "type": "OBJS",
            "roomid": 0,
            "layerid": 0,
            "stageid": "F301_1"
        },
        {
            "params1": "03 00 01 0A",
            "params2": "FF 5F FF 17",
            "posx": 1786.7740478515625,
            "posy": -10000.0,
            "posz": -736.3787231445312,
            "anglex": 65535,
            "angley": 0,
            "anglez": 65535,
            "id": "FC 4E",
            "name": "saveObj",
            "extra_info": {
                "scenefid": 10,
                "scenef": "scene flag: 0x0 04",
                "subtype": "overworld",
                "scen_link": 0,
                "saveobj_name_id": 23,
                "name": "Ancient Harbor"
            },
            "type": "OBJS",
            "roomid": 0,
            "layerid": 0,
            "stageid": "F301_1"
        },
        {
            "params1": "03 00 00 56",
            "params2": "FF 5F FF FF",
            "posx": -120725.90625,
            "posy": -10000.0,
            "posz": 11223.767578125,
            "anglex": 65535,
            "angley": 0,
            "anglez": 65535,
            "id": "FC 4F",
            "name": "saveObj",
            "extra_info": {
                "scenefid": 86,
                "scenef": "scene flag: 0xB 40",
                "subtype": "normal",
                "scen_link": 0,
                "saveobj_name_id": 255,
                "name": "Bird Statue"
            },
            "type": "OBJS",
            "roomid": 0,
            "layerid": 0,
            "stageid": "F301_1"
        }
    ],
    "F301_3": [
        {
            "params1": "03 01 01 1C",
            "params2": "FF 5F FF 18",
            "posx": -3945.95556640625,
            "posy": 50.0,
            "posz": 8660.505859375,
            "anglex": 65535,
            "angley": 16384,
            "anglez": 65535,
            "id": "FC 07",
            "name": "saveObj",
            "extra_info": {
                "scenefid": 28,
                "scenef": "scene flag: 0x2 10",
                "subtype": "overworld",
                "scen_link": 1,
                "saveobj_name_id": 24,
                "name": "Skipper's Retreat"
            },
            "type": "OBJS",
            "roomid": 0,
            "layerid": 0,
            "stageid": "F301_3"
        }
    ],
    "F301_4": [
        {
            "params1": "03 01 01 55",
            "params2": "FF 5F FF 19",
            "posx": -414.7913818359375,
            "posy": 50.0,
            "posz": 15822.5751953125,
            "anglex": 65535,
            "angley": 0,
            "anglez": 65535,
            "id": "FC 04",
            "name": "saveObj",
            "extra_info": {
                "scenefid": 85,
                "scenef": "scene flag: 0xB 20",
                "subtype": "overworld",
                "scen_link": 1,
                "saveobj_name_id": 25,
                "name": "Shipyard"
            },
            "type": "OBJS",
            "roomid": 0,
            "layerid": 0,
            "stageid": "F301_4"
        },
        {
            "params1": "03 08 00 56",
            "params2": "FF 5F FF FF",
            "posx": -3983.5419921875,
            "posy": 500.0,
            "posz": 8826.5927734375,
            "anglex": 65535,
            "angley": 0,
            "anglez": 65535,
            "id": "00 17",
            "name": "saveObj",
            "extra_info": {
                "scenefid": 86,
                "scenef": "scene flag: 0xB 40",
                "subtype": "normal",
                "scen_link": 8,
                "saveobj_name_id": 255,
                "name": "Bird Statue",
                "viewclip_index": 0
            },
            "type": "OBJS",
            "roomid": 0,
            "layerid": 0,
            "stageid": "F301_4"
        }
    ],
    "F301_6": [
        {
            "params1": "03 03 01 54",
            "params2": "FF 5F FF 1A",
            "posx": -712.8203735351562,
            "posy": 70.0,
            "posz": 182.49331665039062,
            "anglex": 65535,
            "angley": 0,
            "anglez": 65535,
            "id": "FC 09",
            "name": "saveObj",
            "extra_info": {
                "scenefid": 84,
                "scenef": "scene flag: 0xB 10",
                "subtype": "overworld",
                "scen_link": 3,
                "saveobj_name_id": 26,
                "name": "Pirate Stronghold"
            },
            "type": "OBJS",
            "roomid": 0,
            "layerid": 0,
            "stageid": "F301_6"
        }
    ],
    "F302": [
        {
            "params1": "03 01 01 0C",
            "params2": "FF 5F FF 1B",
            "posx": -1200.0,
            "posy": 30.0,
            "posz": -2000.0,
            "anglex": 65535,
            "angley": 16384,
            "anglez": 65535,
            "id": "00 16",
            "name": "saveObj",
            "extra_info": {
                "scenefid": 12,
                "scenef": "scene flag: 0x0 10",
                "subtype": "overworld",
                "scen_link": 1,
                "saveobj_name_id": 27,
                "name": "Lanayru Gorge",
                "viewclip_index": 0
            },
            "type": "OBJS",
            "roomid": 0,
            "layerid": 0,
            "stageid": "F302"
        }
    ],
    "F400": [
        {
            "params1": "01 05 01 1F",
            "params2": "FF 5F FF 00",
            "posx": -11029.0810546875,
            "posy": 7500.0,
            "posz": 6279.25146484375,
            "anglex": 65535,
            "angley": 14199,
            "anglez": 65535,
            "id": "FC 2B",
            "name": "saveObj",
            "extra_info": {
                "scenefid": 31,
                "scenef": "scene flag: 0x2 80",
                "subtype": "overworld",
                "scen_link": 5,
                "saveobj_name_id": 0,
                "name": "Behind the Temple"
            },
            "type": "OBJS",
            "roomid": 0,
            "layerid": 0,
            "stageid": "F400"
        },
        {
            "params1": "FF FF 00 20",
            "params2": "FF 5F FF FF",
            "posx": 1365.0419921875,
            "posy": 7600.0,
            "posz": 10420.0068359375,
            "anglex": 65535,
            "angley": 49152,
            "anglez": 65535,
            "id": "FC 4F",
            "name": "saveObj",
            "extra_info": {
                "scenefid": 32,
                "scenef": "scene flag: 0x5 01",
                "subtype": "normal",
                "scen_link": 255,
                "saveobj_name_id": 255,
                "name": "Bird Statue"
            },
            "type": "OBJS",
            "roomid": 0,
            "layerid": 0,
            "stageid": "F400"
        },
        {
            "params1": "01 13 01 23",
            "params2": "FF 5F FF 1C",
            "posx": -8043.06689453125,
            "posy": 8403.87890625,
            "posz": 153.0,
            "anglex": 65535,
            "angley": 17840,
            "anglez": 65535,
            "id": "FC 58",
            "name": "saveObj",
            "extra_info": {
                "scenefid": 35,
                "scenef": "scene flag: 0x5 08",
                "subtype": "overworld",
                "scen_link": 19,
                "saveobj_name_id": 28,
                "name": "Sealed Grounds"
            },
            "type": "OBJS",
            "roomid": 0,
            "layerid": 0,
            "stageid": "F400"
        }
    ],
    "F401": [
        {
            "params1": "01 05 01 1F",
            "params2": "FF 5F FF 00",
            "posx": -11029.0810546875,
            "posy": 7500.0,
            "posz": 6279.25146484375,
            "anglex": 65535,
            "angley": 14199,
            "anglez": 65535,
            "id": "FC 0C",
            "name": "saveObj",
            "extra_info": {
                "scenefid": 31,
                "scenef": "scene flag: 0x2 80",
                "subtype": "overworld",
                "scen_link": 5,
                "saveobj_name_id": 0,
                "name": "Behind the Temple"
            },
            "type": "OBJS",
            "roomid": 1,
            "layerid": 0,
            "stageid": "F401"
        },
        {
            "params1": "FF FF 00 20",
            "params2": "FF 5F FF FF",
            "posx": 1365.0419921875,
            "posy": 7600.0,
            "posz": 10420.0068359375,
            "anglex": 65535,
            "angley": 49152,
            "anglez": 65535,
            "id": "FC 0D",
            "name": "saveObj",
            "extra_info": {
                "scenefid": 32,
                "scenef": "scene flag: 0x5 01",
                "subtype": "normal",
                "scen_link": 255,
                "saveobj_name_id": 255,
                "name": "Bird Statue"
            },
            "type": "OBJS",
            "roomid": 1,
            "layerid": 0,
            "stageid": "F401"
        },
        {
            "params1": "01 13 01 23",
            "params2": "FF 5F FF 1C",
            "posx": -8043.06689453125,
            "posy": 8403.87890625,
            "posz": 153.0,
            "anglex": 65535,
            "angley": 17840,
            "anglez": 65535,
            "id": "FC 12",
            "name": "saveObj",
            "extra_info": {
                "scenefid": 35,
                "scenef": "scene flag: 0x5 08",
                "subtype": "overworld",
                "scen_link": 19,
                "saveobj_name_id": 28,
                "name": "Sealed Grounds"
            },
            "type": "OBJS",
            "roomid": 1,
            "layerid": 0,
            "stageid": "F401"
        }
    ],
    "F402": [
        {
            "params1": "FF FF 00 20",
            "params2": "FF 5F FF FF",
            "posx": 1365.0419921875,
            "posy": 7600.0,
            "posz": 10420.0068359375,
            "anglex": 65535,
            "angley": 49152,
            "anglez": 65535,
            "id": "FC 02",
            "name": "saveObj",
            "extra_info": {
                "scenefid": 32,
                "scenef": "scene flag: 0x5 01",
                "subtype": "normal",
                "scen_link": 255,
                "saveobj_name_id": 255,
                "name": "Bird Statue"
            },
            "type": "OBJS",
            "roomid": 2,
            "layerid": 0,
            "stageid": "F402"
        },
        {
            "params1": "01 05 01 1F",
            "params2": "FF 5F FF 00",
            "posx": -11029.0810546875,
            "posy": 7500.0,
            "posz": 6279.25146484375,
            "anglex": 65535,
            "angley": 14199,
            "anglez": 65535,
            "id": "FC 25",
            "name": "saveObj",
            "extra_info": {
                "scenefid": 31,
                "scenef": "scene flag: 0x2 80",
                "subtype": "overworld",
                "scen_link": 5,
                "saveobj_name_id": 0,
                "name": "Behind the Temple"
            },
            "type": "OBJS",
            "roomid": 2,
            "layerid": 0,
            "stageid": "F402"
        },
        {
            "params1": "01 13 01 23",
            "params2": "FF 5F FF 1C",
            "posx": -8043.06689453125,
            "posy": 8403.87890625,
            "posz": 153.0,
            "anglex": 65535,
            "angley": 17840,
            "anglez": 65535,
            "id": "FC 29",
            "name": "saveObj",
            "extra_info": {
                "scenefid": 35,
                "scenef": "scene flag: 0x5 08",
                "subtype": "overworld",
                "scen_link": 19,
                "saveobj_name_id": 28,
                "name": "Sealed Grounds"
            },
            "type": "OBJS",
            "roomid": 2,
            "layerid": 0,
            "stageid": "F402"
        }
    ],
    "F403": [
        {
            "params1": "FF FF 00 21",
            "params2": "FF 5F FF FF",
            "posx": 0.0,
            "posy": 0.8700000047683716,
            "posz": 2320.0,
            "anglex": 65535,
            "angley": 32768,
            "anglez": 65535,
            "id": "04 01",
            "name": "saveObj",
            "extra_info": {
                "scenefid": 33,
                "scenef": "scene flag: 0x5 02",
                "subtype": "normal",
                "scen_link": 255,
                "saveobj_name_id": 255,
                "name": "Bird Statue",
                "viewclip_index": 1
            },
            "type": "OBJS",
            "roomid": 1,
            "layerid": 0,
            "stageid": "F403"
        },
        {
            "params1": "FF FF 00 22",
            "params2": "FF 5F FF FF",
            "posx": 1365.0419921875,
            "posy": 7600.0,
            "posz": 10420.0068359375,
            "anglex": 65535,
            "angley": 49152,
            "anglez": 65535,
            "id": "FC 08",
            "name": "saveObj",
            "extra_info": {
                "scenefid": 34,
                "scenef": "scene flag: 0x5 04",
                "subtype": "normal",
                "scen_link": 255,
                "saveobj_name_id": 255,
                "name": "Bird Statue"
            },
            "type": "OBJS",
            "roomid": 1,
            "layerid": 0,
            "stageid": "F403"
        }
    ],
    "F404": [
        {
            "params1": "FF FF 00 22",
            "params2": "FF 5F FF FF",
            "posx": 1365.0419921875,
            "posy": 7600.0,
            "posz": 10420.0068359375,
            "anglex": 65535,
            "angley": 49152,
            "anglez": 65535,
            "id": "FC 06",
            "name": "saveObj",
            "extra_info": {
                "scenefid": 34,
                "scenef": "scene flag: 0x5 04",
                "subtype": "normal",
                "scen_link": 255,
                "saveobj_name_id": 255,
                "name": "Bird Statue"
            },
            "type": "OBJS",
            "roomid": 2,
            "layerid": 0,
            "stageid": "F404"
        },
        {
            "params1": "FF FF 00 21",
            "params2": "FF 5F FF FF",
            "posx": 0.0,
            "posy": 0.8700000047683716,
            "posz": 2320.0,
            "anglex": 65535,
            "angley": 32768,
            "anglez": 65535,
            "id": "FC 0B",
            "name": "saveObj",
            "extra_info": {
                "scenefid": 33,
                "scenef": "scene flag: 0x5 02",
                "subtype": "normal",
                "scen_link": 255,
                "saveobj_name_id": 255,
                "name": "Bird Statue"
            },
            "type": "OBJS",
            "roomid": 2,
            "layerid": 0,
            "stageid": "F404"
        }
    ],
    "F406": [
        {
            "params1": "01 05 01 1F",
            "params2": "FF 5F FF 00",
            "posx": -11029.0810546875,
            "posy": 7500.0,
            "posz": 6279.25146484375,
            "anglex": 65535,
            "angley": 14199,
            "anglez": 65535,
            "id": "FC 01",
            "name": "saveObj",
            "extra_info": {
                "scenefid": 31,
                "scenef": "scene flag: 0x2 80",
                "subtype": "overworld",
                "scen_link": 5,
                "saveobj_name_id": 0,
                "name": "Behind the Temple"
            },
            "type": "OBJS",
            "roomid": 1,
            "layerid": 0,
            "stageid": "F406"
        },
        {
            "params1": "FF FF 00 20",
            "params2": "FF 5F FF FF",
            "posx": 1365.0419921875,
            "posy": 7600.0,
            "posz": 10420.0068359375,
            "anglex": 65535,
            "angley": 49152,
            "anglez": 65535,
            "id": "FC 04",
            "name": "saveObj",
            "extra_info": {
                "scenefid": 32,
                "scenef": "scene flag: 0x5 01",
                "subtype": "normal",
                "scen_link": 255,
                "saveobj_name_id": 255,
                "name": "Bird Statue"
            },
            "type": "OBJS",
            "roomid": 1,
            "layerid": 0,
            "stageid": "F406"
        },
        {
            "params1": "01 10 01 23",
            "params2": "FF 5F FF 1D",
            "posx": -8043.06689453125,
            "posy": 8391.205078125,
            "posz": 153.0,
            "anglex": 65535,
            "angley": 17840,
            "anglez": 65535,
            "id": "FC 08",
            "name": "saveObj",
            "extra_info": {
                "scenefid": 35,
                "scenef": "scene flag: 0x5 08",
                "subtype": "overworld",
                "scen_link": 16,
                "saveobj_name_id": 29,
                "name": "Sealed Grounds"
            },
            "type": "OBJS",
            "roomid": 1,
            "layerid": 0,
            "stageid": "F406"
        }
    ]
}